crflux/GSF_spline_20171007.pkl.bz2
crflux/__init__.py
crflux/models.py
crflux-1.0.6.dist-info/LICENSE
crflux-1.0.6.dist-info/METADATA
crflux-1.0.6.dist-info/WHEEL
crflux-1.0.6.dist-info/top_level.txt
crflux-1.0.6.dist-info/RECORD
