Metadata-Version: 2.1
Name: crflux
Version: 1.0.6
Summary: Parameterizations of the cosmic ray flux at Earth
Home-page: https://github.com/afedynitch/crflux
Author: Anatoli Fedynitch
Author-email: afedynitch@gmail.com
License: MIT
Platform: UNKNOWN
Classifier: Programming Language :: Python
Classifier: Programming Language :: Python :: 2
Classifier: Programming Language :: Python :: 2.7
Classifier: Programming Language :: Python :: 3
Classifier: Programming Language :: Python :: 3.5
Classifier: Programming Language :: Python :: 3.6
Classifier: Programming Language :: Python :: 3.7
Classifier: Programming Language :: Python :: 3.8
Classifier: Topic :: Scientific/Engineering :: Physics
Classifier: Intended Audience :: Science/Research
Classifier: Development Status :: 5 - Production/Stable
Classifier: License :: OSI Approved :: MIT License
Requires-Dist: setuptools
Requires-Dist: numpy
Requires-Dist: scipy
Provides-Extra: tests
Requires-Dist: pytest ; extra == 'tests'
Requires-Dist: matplotlib ; extra == 'tests'
